ServerMonPy/__init__.py
ServerMonPy/main.py.py
tests/__init__.py
tests/test_main.py
ServerMonPy-0.0.1.dist-info/LICENSE
ServerMonPy-0.0.1.dist-info/METADATA
ServerMonPy-0.0.1.dist-info/WHEEL
ServerMonPy-0.0.1.dist-info/entry_points.txt
ServerMonPy-0.0.1.dist-info/top_level.txt
ServerMonPy-0.0.1.dist-info/RECORD
