Metadata-Version: 2.1
Name: ServerMonPy
Version: 0.0.1
Summary: Real-time server monitoring tool using SSH
Home-page: https://github.com/rubikproxy/ServerMonPy
Author: sanjay,suresh,logu
Author-email: SANJAY <rubikproxy@gmail.com>
Project-URL: Homepage, https://github.com/rubikproxy/ServerMonPy
Project-URL: Bug Tracker, https://github.com/rubikproxy/ServerMonPy/issues
Classifier: Programming Language :: Python :: 3
Classifier: License :: OSI Approved :: MIT License
Classifier: Operating System :: OS Independent
Requires-Python: >=3.6
License-File: LICENSE
Requires-Dist: paramiko ==2.8.0
Requires-Dist: psutil ==5.8.0
